string_booster/__init__.py
string_booster/string_booster.py
string_booster_pack-1.0.0.dist-info/METADATA
string_booster_pack-1.0.0.dist-info/WHEEL
string_booster_pack-1.0.0.dist-info/top_level.txt
string_booster_pack-1.0.0.dist-info/RECORD
