Metadata-Version: 2.1
Name: string-booster-pack
Version: 1.0.0
Summary: Some semi-useful functions for strings
Home-page: https://github.com/coy0tecode/String-Booster-Pack
Author: coy0tecode
Author-email: mjt5224@gmail.com
License: MIT
Platform: UNKNOWN
Classifier: License :: OSI Approved :: MIT License
Classifier: Programming Language :: Python :: 3
